{
  "name": "pg-ridgeline",
  "type": "dark",
  "semanticHighlighting": true,
  "semanticTokenColors": {
    "enumMember": {
      "foreground": "#f9ed41"
    },
    "variable.constant": {
      "foreground": "#c75f5f"
    },
    "variable.defaultLibrary": {
      "foreground": "#8b965e"
    }
  },
  "tokenColors": [
    {
      "name": "unison punctuation",
      "scope": "punctuation.definition.delayed.unison,punctuation.definition.list.begin.unison,punctuation.definition.list.end.unison,punctuation.definition.ability.begin.unison,punctuation.definition.ability.end.unison,punctuation.operator.assignment.as.unison,punctuation.separator.pipe.unison,punctuation.separator.delimiter.unison,punctuation.definition.hash.unison",
      "settings": {
        "foreground": "#d0d370"
      }
    },
    {
      "name": "haskell variable generic-type",
      "scope": "variable.other.generic-type.haskell",
      "settings": {
        "foreground": "#f3b82c"
      }
    },
    {
      "name": "haskell storage type",
      "scope": "storage.type.haskell",
      "settings": {
        "foreground": "#c75f5f"
      }
    },
    {
      "name": "support.variable.magic.python",
      "scope": "support.variable.magic.python",
      "settings": {
        "foreground": "#d0d370"
      }
    },
    {
      "name": "punctuation.separator.parameters.python",
      "scope": "punctuation.separator.period.python,punctuation.separator.element.python,punctuation.parenthesis.begin.python,punctuation.parenthesis.end.python",
      "settings": {
        "foreground": "#a9c2c1e3"
      }
    },
    {
      "name": "variable.parameter.function.language.special.self.python",
      "scope": "variable.parameter.function.language.special.self.python",
      "settings": {
        "foreground": "#8b965e"
      }
    },
    {
      "name": "storage.modifier.lifetime.rust",
      "scope": "storage.modifier.lifetime.rust",
      "settings": {
        "foreground": "#a9c2c1e3"
      }
    },
    {
      "name": "support.function.std.rust",
      "scope": "support.function.std.rust",
      "settings": {
        "foreground": "#579f91"
      }
    },
    {
      "name": "entity.name.lifetime.rust",
      "scope": "entity.name.lifetime.rust",
      "settings": {
        "foreground": "#8b965e"
      }
    },
    {
      "name": "variable.language.rust",
      "scope": "variable.language.rust",
      "settings": {
        "foreground": "#d0d370"
      }
    },
    {
      "name": "support.constant.edge",
      "scope": "support.constant.edge",
      "settings": {
        "foreground": "#f3b82c"
      }
    },
    {
      "name": "regexp constant character-class",
      "scope": "constant.other.character-class.regexp",
      "settings": {
        "foreground": "#d0d370"
      }
    },
    {
      "name": "regexp operator.quantifier",
      "scope": "keyword.operator.quantifier.regexp",
      "settings": {
        "foreground": "#c75f5f"
      }
    },
    {
      "name": "punctuation.definition",
      "scope": "punctuation.definition.string.begin,punctuation.definition.string.end",
      "settings": {
        "foreground": "#c75f5f"
      }
    },
    {
      "name": "Text",
      "scope": "variable.parameter.function",
      "settings": {
        "foreground": "#a9c2c1e3"
      }
    },
    {
      "name": "Comment Markup Link",
      "scope": "comment markup.link",
      "settings": {
        "foreground": "#686451"
      }
    },
    {
      "name": "markup diff",
      "scope": "markup.changed.diff",
      "settings": {
        "foreground": "#8b965e"
      }
    },
    {
      "name": "diff",
      "scope": "meta.diff.header.from-file,meta.diff.header.to-file,punctuation.definition.from-file.diff,punctuation.definition.to-file.diff",
      "settings": {
        "foreground": "#579f91"
      }
    },
    {
      "name": "inserted.diff",
      "scope": "markup.inserted.diff",
      "settings": {
        "foreground": "#c75f5f"
      }
    },
    {
      "name": "deleted.diff",
      "scope": "markup.deleted.diff",
      "settings": {
        "foreground": "#d0d370"
      }
    },
    {
      "name": "c++ function",
      "scope": "meta.function.c,meta.function.cpp",
      "settings": {
        "foreground": "#d0d370"
      }
    },
    {
      "name": "c++ block",
      "scope": "punctuation.section.block.begin.bracket.curly.cpp,punctuation.section.block.end.bracket.curly.cpp,punctuation.terminator.statement.c,punctuation.section.block.begin.bracket.curly.c,punctuation.section.block.end.bracket.curly.c,punctuation.section.parens.begin.bracket.round.c,punctuation.section.parens.end.bracket.round.c,punctuation.section.parameters.begin.bracket.round.c,punctuation.section.parameters.end.bracket.round.c",
      "settings": {
        "foreground": "#a9c2c1e3"
      }
    },
    {
      "name": "js/ts punctuation separator key-value",
      "scope": "punctuation.separator.key-value",
      "settings": {
        "foreground": "#a9c2c1e3"
      }
    },
    {
      "name": "js/ts import keyword",
      "scope": "keyword.operator.expression.import",
      "settings": {
        "foreground": "#579f91"
      }
    },
    {
      "name": "math js/ts",
      "scope": "support.constant.math",
      "settings": {
        "foreground": "#8b965e"
      }
    },
    {
      "name": "math property js/ts",
      "scope": "support.constant.property.math",
      "settings": {
        "foreground": "#c75f5f"
      }
    },
    {
      "name": "js/ts variable.other.constant",
      "scope": "variable.other.constant",
      "settings": {
        "foreground": "#8b965e"
      }
    },
    {
      "name": "java type",
      "scope": [
        "storage.type.annotation.java",
        "storage.type.object.array.java"
      ],
      "settings": {
        "foreground": "#8b965e"
      }
    },
    {
      "name": "java source",
      "scope": "source.java",
      "settings": {
        "foreground": "#d0d370"
      }
    },
    {
      "name": "java modifier.import",
      "scope": "punctuation.section.block.begin.java,punctuation.section.block.end.java,punctuation.definition.method-parameters.begin.java,punctuation.definition.method-parameters.end.java,meta.method.identifier.java,punctuation.section.method.begin.java,punctuation.section.method.end.java,punctuation.terminator.java,punctuation.section.class.begin.java,punctuation.section.class.end.java,punctuation.section.inner-class.begin.java,punctuation.section.inner-class.end.java,meta.method-call.java,punctuation.section.class.begin.bracket.curly.java,punctuation.section.class.end.bracket.curly.java,punctuation.section.method.begin.bracket.curly.java,punctuation.section.method.end.bracket.curly.java,punctuation.separator.period.java,punctuation.bracket.angle.java,punctuation.definition.annotation.java,meta.method.body.java",
      "settings": {
        "foreground": "#a9c2c1e3"
      }
    },
    {
      "name": "java modifier.import",
      "scope": "meta.method.java",
      "settings": {
        "foreground": "#579f91"
      }
    },
    {
      "name": "java modifier.import",
      "scope": "storage.modifier.import.java,storage.type.java,storage.type.generic.java",
      "settings": {
        "foreground": "#8b965e"
      }
    },
    {
      "name": "java instanceof",
      "scope": "keyword.operator.instanceof.java",
      "settings": {
        "foreground": "#f3b82c"
      }
    },
    {
      "name": "java variable.name",
      "scope": "meta.definition.variable.name.java",
      "settings": {
        "foreground": "#d0d370"
      }
    },
    {
      "name": "operator logical",
      "scope": "keyword.operator.logical",
      "settings": {
        "foreground": "#f9ed41"
      }
    },
    {
      "name": "operator bitwise",
      "scope": "keyword.operator.bitwise",
      "settings": {
        "foreground": "#f9ed41"
      }
    },
    {
      "name": "operator channel",
      "scope": "keyword.operator.channel",
      "settings": {
        "foreground": "#f9ed41"
      }
    },
    {
      "name": "support.constant.property-value.scss",
      "scope": "support.constant.property-value.scss,support.constant.property-value.css",
      "settings": {
        "foreground": "#c75f5f"
      }
    },
    {
      "name": "CSS/SCSS/LESS Operators",
      "scope": "keyword.operator.css,keyword.operator.scss,keyword.operator.less",
      "settings": {
        "foreground": "#f9ed41"
      }
    },
    {
      "name": "css color standard name",
      "scope": "support.constant.color.w3c-standard-color-name.css,support.constant.color.w3c-standard-color-name.scss",
      "settings": {
        "foreground": "#c75f5f"
      }
    },
    {
      "name": "css comma",
      "scope": "punctuation.separator.list.comma.css",
      "settings": {
        "foreground": "#a9c2c1e3"
      }
    },
    {
      "name": "css attribute-name.id",
      "scope": "support.constant.color.w3c-standard-color-name.css",
      "settings": {
        "foreground": "#c75f5f"
      }
    },
    {
      "name": "css property-name",
      "scope": "support.type.vendored.property-name.css",
      "settings": {
        "foreground": "#f9ed41"
      }
    },
    {
      "name": "js/ts module",
      "scope": "support.module.node,support.type.object.module,support.module.node",
      "settings": {
        "foreground": "#8b965e"
      }
    },
    {
      "name": "entity.name.type.module",
      "scope": "entity.name.type.module",
      "settings": {
        "foreground": "#8b965e"
      }
    },
    {
      "name": "js variable readwrite",
      "scope": "variable.other.readwrite,meta.object-literal.key,support.variable.property,support.variable.object.process,support.variable.object.node",
      "settings": {
        "foreground": "#d0d370"
      }
    },
    {
      "name": "js/ts json",
      "scope": "support.constant.json",
      "settings": {
        "foreground": "#c75f5f"
      }
    },
    {
      "name": "js/ts Keyword",
      "scope": [
        "keyword.operator.expression.instanceof",
        "keyword.operator.new",
        "keyword.operator.ternary",
        "keyword.operator.optional",
        "keyword.operator.expression.keyof"
      ],
      "settings": {
        "foreground": "#f3b82c"
      }
    },
    {
      "name": "js/ts console",
      "scope": "support.type.object.console",
      "settings": {
        "foreground": "#d0d370"
      }
    },
    {
      "name": "js/ts support.variable.property.process",
      "scope": "support.variable.property.process",
      "settings": {
        "foreground": "#c75f5f"
      }
    },
    {
      "name": "js console function",
      "scope": "entity.name.function,support.function.console",
      "settings": {
        "foreground": "#579f91"
      }
    },
    {
      "name": "keyword.operator.misc.rust",
      "scope": "keyword.operator.misc.rust",
      "settings": {
        "foreground": "#a9c2c1e3"
      }
    },
    {
      "name": "keyword.operator.sigil.rust",
      "scope": "keyword.operator.sigil.rust",
      "settings": {
        "foreground": "#f3b82c"
      }
    },
    {
      "name": "operator",
      "scope": "keyword.operator.delete",
      "settings": {
        "foreground": "#f3b82c"
      }
    },
    {
      "name": "js dom",
      "scope": "support.type.object.dom",
      "settings": {
        "foreground": "#f9ed41"
      }
    },
    {
      "name": "js dom variable",
      "scope": "support.variable.dom,support.variable.property.dom",
      "settings": {
        "foreground": "#d0d370"
      }
    },
    {
      "name": "keyword.operator",
      "scope": "keyword.operator.arithmetic,keyword.operator.comparison,keyword.operator.decrement,keyword.operator.increment,keyword.operator.relational",
      "settings": {
        "foreground": "#f9ed41"
      }
    },
    {
      "name": "C operator assignment",
      "scope": "keyword.operator.assignment.c,keyword.operator.comparison.c,keyword.operator.c,keyword.operator.increment.c,keyword.operator.decrement.c,keyword.operator.bitwise.shift.c,keyword.operator.assignment.cpp,keyword.operator.comparison.cpp,keyword.operator.cpp,keyword.operator.increment.cpp,keyword.operator.decrement.cpp,keyword.operator.bitwise.shift.cpp",
      "settings": {
        "foreground": "#f3b82c"
      }
    },
    {
      "name": "Punctuation",
      "scope": "punctuation.separator.delimiter",
      "settings": {
        "foreground": "#a9c2c1e3"
      }
    },
    {
      "name": "Other punctuation .c",
      "scope": "punctuation.separator.c,punctuation.separator.cpp",
      "settings": {
        "foreground": "#f3b82c"
      }
    },
    {
      "name": "C type posix-reserved",
      "scope": "support.type.posix-reserved.c,support.type.posix-reserved.cpp",
      "settings": {
        "foreground": "#f9ed41"
      }
    },
    {
      "name": "keyword.operator.sizeof.c",
      "scope": "keyword.operator.sizeof.c,keyword.operator.sizeof.cpp",
      "settings": {
        "foreground": "#f3b82c"
      }
    },
    {
      "name": "python parameter",
      "scope": "variable.parameter.function.language.python",
      "settings": {
        "foreground": "#c75f5f"
      }
    },
    {
      "name": "python type",
      "scope": "support.type.python",
      "settings": {
        "foreground": "#f9ed41"
      }
    },
    {
      "name": "python logical",
      "scope": "keyword.operator.logical.python",
      "settings": {
        "foreground": "#f3b82c"
      }
    },
    {
      "name": "pyCs",
      "scope": "variable.parameter.function.python",
      "settings": {
        "foreground": "#c75f5f"
      }
    },
    {
      "name": "python block",
      "scope": "punctuation.definition.arguments.begin.python,punctuation.definition.arguments.end.python,punctuation.separator.arguments.python,punctuation.definition.list.begin.python,punctuation.definition.list.end.python",
      "settings": {
        "foreground": "#a9c2c1e3"
      }
    },
    {
      "name": "python function-call.generic",
      "scope": "meta.function-call.generic.python",
      "settings": {
        "foreground": "#579f91"
      }
    },
    {
      "name": "python placeholder reset to normal string",
      "scope": "constant.character.format.placeholder.other.python",
      "settings": {
        "foreground": "#c75f5f"
      }
    },
    {
      "name": "Operators",
      "scope": "keyword.operator",
      "settings": {
        "foreground": "#a9c2c1e3"
      }
    },
    {
      "name": "Compound Assignment Operators",
      "scope": "keyword.operator.assignment.compound",
      "settings": {
        "foreground": "#f3b82c"
      }
    },
    {
      "name": "Compound Assignment Operators js/ts",
      "scope": "keyword.operator.assignment.compound.js,keyword.operator.assignment.compound.ts",
      "settings": {
        "foreground": "#f9ed41"
      }
    },
    {
      "name": "Keywords",
      "scope": "keyword",
      "settings": {
        "foreground": "#f3b82c"
      }
    },
    {
      "name": "Namespaces",
      "scope": "entity.name.namespace",
      "settings": {
        "foreground": "#8b965e"
      }
    },
    {
      "name": "Variables",
      "scope": "variable",
      "settings": {
        "foreground": "#d0d370"
      }
    },
    {
      "name": "Variables",
      "scope": "variable.c",
      "settings": {
        "foreground": "#a9c2c1e3"
      }
    },
    {
      "name": "Language variables",
      "scope": "variable.language",
      "settings": {
        "foreground": "#8b965e"
      }
    },
    {
      "name": "Java Variables",
      "scope": "token.variable.parameter.java",
      "settings": {
        "foreground": "#a9c2c1e3"
      }
    },
    {
      "name": "Java Imports",
      "scope": "import.storage.java",
      "settings": {
        "foreground": "#8b965e"
      }
    },
    {
      "name": "Packages",
      "scope": "token.package.keyword",
      "settings": {
        "foreground": "#f3b82c"
      }
    },
    {
      "name": "Packages",
      "scope": "token.package",
      "settings": {
        "foreground": "#a9c2c1e3"
      }
    },
    {
      "name": "Functions",
      "scope": [
        "entity.name.function",
        "meta.require",
        "support.function.any-method",
        "variable.function"
      ],
      "settings": {
        "foreground": "#579f91"
      }
    },
    {
      "name": "Classes",
      "scope": "entity.name.type.namespace",
      "settings": {
        "foreground": "#8b965e"
      }
    },
    {
      "name": "Classes",
      "scope": "support.class, entity.name.type.class",
      "settings": {
        "foreground": "#8b965e"
      }
    },
    {
      "name": "Class name",
      "scope": "entity.name.class.identifier.namespace.type",
      "settings": {
        "foreground": "#8b965e"
      }
    },
    {
      "name": "Class name",
      "scope": [
        "entity.name.class",
        "variable.other.class.js",
        "variable.other.class.ts"
      ],
      "settings": {
        "foreground": "#8b965e"
      }
    },
    {
      "name": "Class name php",
      "scope": "variable.other.class.php",
      "settings": {
        "foreground": "#d0d370"
      }
    },
    {
      "name": "Type Name",
      "scope": "entity.name.type",
      "settings": {
        "foreground": "#8b965e"
      }
    },
    {
      "name": "Keyword Control",
      "scope": "keyword.control",
      "settings": {
        "foreground": "#f3b82c"
      }
    },
    {
      "name": "Control Elements",
      "scope": "control.elements, keyword.operator.less",
      "settings": {
        "foreground": "#c75f5f"
      }
    },
    {
      "name": "Methods",
      "scope": "keyword.other.special-method",
      "settings": {
        "foreground": "#579f91"
      }
    },
    {
      "name": "Storage",
      "scope": "storage",
      "settings": {
        "foreground": "#f3b82c"
      }
    },
    {
      "name": "Storage JS TS",
      "scope": "token.storage",
      "settings": {
        "foreground": "#f3b82c"
      }
    },
    {
      "name": "Source Js Keyword Operator Delete,source Js Keyword Operator In,source Js Keyword Operator Of,source Js Keyword Operator Instanceof,source Js Keyword Operator New,source Js Keyword Operator Typeof,source Js Keyword Operator Void",
      "scope": "keyword.operator.expression.delete,keyword.operator.expression.in,keyword.operator.expression.of,keyword.operator.expression.instanceof,keyword.operator.new,keyword.operator.expression.typeof,keyword.operator.expression.void",
      "settings": {
        "foreground": "#f3b82c"
      }
    },
    {
      "name": "Java Storage",
      "scope": "token.storage.type.java",
      "settings": {
        "foreground": "#8b965e"
      }
    },
    {
      "name": "Support",
      "scope": "support.function",
      "settings": {
        "foreground": "#f9ed41"
      }
    },
    {
      "name": "Support type",
      "scope": "support.type.property-name",
      "settings": {
        "foreground": "#a9c2c1e3"
      }
    },
    {
      "name": "Support type",
      "scope": "support.constant.property-value",
      "settings": {
        "foreground": "#a9c2c1e3"
      }
    },
    {
      "name": "Support type",
      "scope": "support.constant.font-name",
      "settings": {
        "foreground": "#c75f5f"
      }
    },
    {
      "name": "Meta tag",
      "scope": "meta.tag",
      "settings": {
        "foreground": "#a9c2c1e3"
      }
    },
    {
      "name": "Strings",
      "scope": "string",
      "settings": {
        "foreground": "#c75f5f"
      }
    },
    {
      "name": "Inherited Class",
      "scope": "entity.other.inherited-class",
      "settings": {
        "foreground": "#8b965e"
      }
    },
    {
      "name": "Constant other symbol",
      "scope": "constant.other.symbol",
      "settings": {
        "foreground": "#f9ed41"
      }
    },
    {
      "name": "Integers",
      "scope": "constant.numeric",
      "settings": {
        "foreground": "#c75f5f"
      }
    },
    {
      "name": "Constants",
      "scope": "constant",
      "settings": {
        "foreground": "#c75f5f"
      }
    },
    {
      "name": "Constants",
      "scope": "punctuation.definition.constant",
      "settings": {
        "foreground": "#c75f5f"
      }
    },
    {
      "name": "Tags",
      "scope": "entity.name.tag",
      "settings": {
        "foreground": "#d0d370"
      }
    },
    {
      "name": "Attributes",
      "scope": "entity.other.attribute-name",
      "settings": {
        "foreground": "#c75f5f"
      }
    },
    {
      "name": "Attribute IDs",
      "scope": "entity.other.attribute-name.id",
      "settings": {
        "fontStyle": "normal",
        "foreground": "#579f91"
      }
    },
    {
      "name": "Attribute class",
      "scope": "entity.other.attribute-name.class.css",
      "settings": {
        "fontStyle": "normal",
        "foreground": "#c75f5f"
      }
    },
    {
      "name": "Selector",
      "scope": "meta.selector",
      "settings": {
        "foreground": "#f3b82c"
      }
    },
    {
      "name": "Headings",
      "scope": "markup.heading",
      "settings": {
        "foreground": "#d0d370"
      }
    },
    {
      "name": "Headings",
      "scope": "markup.heading punctuation.definition.heading, entity.name.section",
      "settings": {
        "foreground": "#579f91"
      }
    },
    {
      "name": "Units",
      "scope": "keyword.other.unit",
      "settings": {
        "foreground": "#d0d370"
      }
    },
    {
      "name": "Bold",
      "scope": "markup.bold,todo.bold",
      "settings": {
        "foreground": "#c75f5f"
      }
    },
    {
      "name": "Bold",
      "scope": "punctuation.definition.bold",
      "settings": {
        "foreground": "#8b965e"
      }
    },
    {
      "name": "markup Italic",
      "scope": "markup.italic, punctuation.definition.italic,todo.emphasis",
      "settings": {
        "foreground": "#f3b82c"
      }
    },
    {
      "name": "emphasis md",
      "scope": "emphasis md",
      "settings": {
        "foreground": "#f3b82c"
      }
    },
    {
      "name": "[VSCODE-CUSTOM] Markdown headings",
      "scope": "entity.name.section.markdown",
      "settings": {
        "foreground": "#d0d370"
      }
    },
    {
      "name": "[VSCODE-CUSTOM] Markdown heading Punctuation Definition",
      "scope": "punctuation.definition.heading.markdown",
      "settings": {
        "foreground": "#d0d370"
      }
    },
    {
      "name": "punctuation.definition.list.begin.markdown",
      "scope": "punctuation.definition.list.begin.markdown",
      "settings": {
        "foreground": "#d0d370"
      }
    },
    {
      "name": "[VSCODE-CUSTOM] Markdown heading setext",
      "scope": "markup.heading.setext",
      "settings": {
        "foreground": "#a9c2c1e3"
      }
    },
    {
      "name": "[VSCODE-CUSTOM] Markdown Punctuation Definition Bold",
      "scope": "punctuation.definition.bold.markdown",
      "settings": {
        "foreground": "#c75f5f"
      }
    },
    {
      "name": "[VSCODE-CUSTOM] Markdown Inline Raw",
      "scope": "markup.inline.raw.markdown",
      "settings": {
        "foreground": "#c75f5f"
      }
    },
    {
      "name": "[VSCODE-CUSTOM] Markdown Inline Raw",
      "scope": "markup.inline.raw.string.markdown",
      "settings": {
        "foreground": "#c75f5f"
      }
    },
    {
      "name": "[VSCODE-CUSTOM] Markdown List Punctuation Definition",
      "scope": "punctuation.definition.list.markdown",
      "settings": {
        "foreground": "#d0d370"
      }
    },
    {
      "name": "[VSCODE-CUSTOM] Markdown Punctuation Definition String",
      "scope": [
        "punctuation.definition.string.begin.markdown",
        "punctuation.definition.string.end.markdown",
        "punctuation.definition.metadata.markdown"
      ],
      "settings": {
        "foreground": "#d0d370"
      }
    },
    {
      "name": "beginning.punctuation.definition.list.markdown",
      "scope": [
        "beginning.punctuation.definition.list.markdown"
      ],
      "settings": {
        "foreground": "#d0d370"
      }
    },
    {
      "name": "[VSCODE-CUSTOM] Markdown Punctuation Definition Link",
      "scope": "punctuation.definition.metadata.markdown",
      "settings": {
        "foreground": "#d0d370"
      }
    },
    {
      "name": "[VSCODE-CUSTOM] Markdown Underline Link/Image",
      "scope": "markup.underline.link.markdown,markup.underline.link.image.markdown",
      "settings": {
        "foreground": "#f3b82c"
      }
    },
    {
      "name": "[VSCODE-CUSTOM] Markdown Link Title/Description",
      "scope": "string.other.link.title.markdown,string.other.link.description.markdown",
      "settings": {
        "foreground": "#579f91"
      }
    },
    {
      "name": "Regular Expressions",
      "scope": "string.regexp",
      "settings": {
        "foreground": "#f9ed41"
      }
    },
    {
      "name": "Escape Characters",
      "scope": "constant.character.escape",
      "settings": {
        "foreground": "#f9ed41"
      }
    },
    {
      "name": "Embedded",
      "scope": "punctuation.section.embedded, variable.interpolation",
      "settings": {
        "foreground": "#d0d370"
      }
    },
    {
      "name": "Embedded",
      "scope": "punctuation.section.embedded.begin,punctuation.section.embedded.end",
      "settings": {
        "foreground": "#f3b82c"
      }
    },
    {
      "name": "illegal",
      "scope": "invalid.illegal",
      "settings": {
        "foreground": "#ffffff"
      }
    },
    {
      "name": "illegal",
      "scope": "invalid.illegal.bad-ampersand.html",
      "settings": {
        "foreground": "#a9c2c1e3"
      }
    },
    {
      "name": "Broken",
      "scope": "invalid.broken",
      "settings": {
        "foreground": "#ffffff"
      }
    },
    {
      "name": "Deprecated",
      "scope": "invalid.deprecated",
      "settings": {
        "foreground": "#ffffff"
      }
    },
    {
      "name": "Unimplemented",
      "scope": "invalid.unimplemented",
      "settings": {
        "foreground": "#ffffff"
      }
    },
    {
      "name": "Source Json Meta Structure Dictionary Json > String Quoted Json",
      "scope": "source.json meta.structure.dictionary.json > string.quoted.json",
      "settings": {
        "foreground": "#d0d370"
      }
    },
    {
      "name": "Source Json Meta Structure Dictionary Json > String Quoted Json > Punctuation String",
      "scope": "source.json meta.structure.dictionary.json > string.quoted.json > punctuation.string",
      "settings": {
        "foreground": "#d0d370"
      }
    },
    {
      "name": "Source Json Meta Structure Dictionary Json > Value Json > String Quoted Json,source Json Meta Structure Array Json > Value Json > String Quoted Json,source Json Meta Structure Dictionary Json > Value Json > String Quoted Json > Punctuation,source Json Meta Structure Array Json > Value Json > String Quoted Json > Punctuation",
      "scope": "source.json meta.structure.dictionary.json > value.json > string.quoted.json,source.json meta.structure.array.json > value.json > string.quoted.json,source.json meta.structure.dictionary.json > value.json > string.quoted.json > punctuation,source.json meta.structure.array.json > value.json > string.quoted.json > punctuation",
      "settings": {
        "foreground": "#c75f5f"
      }
    },
    {
      "name": "Source Json Meta Structure Dictionary Json > Constant Language Json,source Json Meta Structure Array Json > Constant Language Json",
      "scope": "source.json meta.structure.dictionary.json > constant.language.json,source.json meta.structure.array.json > constant.language.json",
      "settings": {
        "foreground": "#f9ed41"
      }
    },
    {
      "name": "[VSCODE-CUSTOM] JSON Property Name",
      "scope": "support.type.property-name.json",
      "settings": {
        "foreground": "#d0d370"
      }
    },
    {
      "name": "[VSCODE-CUSTOM] JSON Punctuation for Property Name",
      "scope": "support.type.property-name.json punctuation",
      "settings": {
        "foreground": "#d0d370"
      }
    },
    {
      "name": "laravel blade tag",
      "scope": "text.html.laravel-blade source.php.embedded.line.html entity.name.tag.laravel-blade",
      "settings": {
        "foreground": "#f3b82c"
      }
    },
    {
      "name": "laravel blade @",
      "scope": "text.html.laravel-blade source.php.embedded.line.html support.constant.laravel-blade",
      "settings": {
        "foreground": "#f3b82c"
      }
    },
    {
      "name": "use statement for other classes",
      "scope": "support.other.namespace.use.php,support.other.namespace.use-as.php,support.other.namespace.php,entity.other.alias.php,meta.interface.php",
      "settings": {
        "foreground": "#8b965e"
      }
    },
    {
      "name": "error suppression",
      "scope": "keyword.operator.error-control.php",
      "settings": {
        "foreground": "#f3b82c"
      }
    },
    {
      "name": "php instanceof",
      "scope": "keyword.operator.type.php",
      "settings": {
        "foreground": "#f3b82c"
      }
    },
    {
      "name": "style double quoted array index normal begin",
      "scope": "punctuation.section.array.begin.php",
      "settings": {
        "foreground": "#a9c2c1e3"
      }
    },
    {
      "name": "style double quoted array index normal end",
      "scope": "punctuation.section.array.end.php",
      "settings": {
        "foreground": "#a9c2c1e3"
      }
    },
    {
      "name": "php illegal.non-null-typehinted",
      "scope": "invalid.illegal.non-null-typehinted.php",
      "settings": {
        "foreground": "#f44747"
      }
    },
    {
      "name": "php types",
      "scope": "storage.type.php,meta.other.type.phpdoc.php,keyword.other.type.php,keyword.other.array.phpdoc.php",
      "settings": {
        "foreground": "#8b965e"
      }
    },
    {
      "name": "php call-function",
      "scope": "meta.function-call.php,meta.function-call.object.php,meta.function-call.static.php",
      "settings": {
        "foreground": "#579f91"
      }
    },
    {
      "name": "php function-resets",
      "scope": "punctuation.definition.parameters.begin.bracket.round.php,punctuation.definition.parameters.end.bracket.round.php,punctuation.separator.delimiter.php,punctuation.section.scope.begin.php,punctuation.section.scope.end.php,punctuation.terminator.expression.php,punctuation.definition.arguments.begin.bracket.round.php,punctuation.definition.arguments.end.bracket.round.php,punctuation.definition.storage-type.begin.bracket.round.php,punctuation.definition.storage-type.end.bracket.round.php,punctuation.definition.array.begin.bracket.round.php,punctuation.definition.array.end.bracket.round.php,punctuation.definition.begin.bracket.round.php,punctuation.definition.end.bracket.round.php,punctuation.definition.begin.bracket.curly.php,punctuation.definition.end.bracket.curly.php,punctuation.definition.section.switch-block.end.bracket.curly.php,punctuation.definition.section.switch-block.start.bracket.curly.php,punctuation.definition.section.switch-block.begin.bracket.curly.php,punctuation.definition.section.switch-block.end.bracket.curly.php",
      "settings": {
        "foreground": "#a9c2c1e3"
      }
    },
    {
      "name": "support php constants",
      "scope": "support.constant.core.rust",
      "settings": {
        "foreground": "#c75f5f"
      }
    },
    {
      "name": "support php constants",
      "scope": "support.constant.ext.php,support.constant.std.php,support.constant.core.php,support.constant.parser-token.php",
      "settings": {
        "foreground": "#c75f5f"
      }
    },
    {
      "name": "php goto",
      "scope": "entity.name.goto-label.php,support.other.php",
      "settings": {
        "foreground": "#579f91"
      }
    },
    {
      "name": "php logical/bitwise operator",
      "scope": "keyword.operator.logical.php,keyword.operator.bitwise.php,keyword.operator.arithmetic.php",
      "settings": {
        "foreground": "#f9ed41"
      }
    },
    {
      "name": "php regexp operator",
      "scope": "keyword.operator.regexp.php",
      "settings": {
        "foreground": "#f3b82c"
      }
    },
    {
      "name": "php comparison",
      "scope": "keyword.operator.comparison.php",
      "settings": {
        "foreground": "#f9ed41"
      }
    },
    {
      "name": "php heredoc/nowdoc",
      "scope": "keyword.operator.heredoc.php,keyword.operator.nowdoc.php",
      "settings": {
        "foreground": "#f3b82c"
      }
    },
    {
      "name": "python function decorator @",
      "scope": "meta.function.decorator.python",
      "settings": {
        "foreground": "#579f91"
      }
    },
    {
      "name": "python function support",
      "scope": "support.token.decorator.python,meta.function.decorator.identifier.python",
      "settings": {
        "foreground": "#f9ed41"
      }
    },
    {
      "name": "parameter function js/ts",
      "scope": "function.parameter",
      "settings": {
        "foreground": "#a9c2c1e3"
      }
    },
    {
      "name": "brace function",
      "scope": "function.brace",
      "settings": {
        "foreground": "#a9c2c1e3"
      }
    },
    {
      "name": "parameter function ruby cs",
      "scope": "function.parameter.ruby, function.parameter.cs",
      "settings": {
        "foreground": "#a9c2c1e3"
      }
    },
    {
      "name": "constant.language.symbol.ruby",
      "scope": "constant.language.symbol.ruby",
      "settings": {
        "foreground": "#f9ed41"
      }
    },
    {
      "name": "rgb-value",
      "scope": "rgb-value",
      "settings": {
        "foreground": "#f9ed41"
      }
    },
    {
      "name": "rgb value",
      "scope": "inline-color-decoration rgb-value",
      "settings": {
        "foreground": "#c75f5f"
      }
    },
    {
      "name": "rgb value less",
      "scope": "less rgb-value",
      "settings": {
        "foreground": "#c75f5f"
      }
    },
    {
      "name": "sass selector",
      "scope": "selector.sass",
      "settings": {
        "foreground": "#d0d370"
      }
    },
    {
      "name": "ts primitive/builtin types",
      "scope": "support.type.primitive.ts,support.type.builtin.ts,support.type.primitive.tsx,support.type.builtin.tsx",
      "settings": {
        "foreground": "#8b965e"
      }
    },
    {
      "name": "block scope",
      "scope": "block.scope.end,block.scope.begin",
      "settings": {
        "foreground": "#a9c2c1e3"
      }
    },
    {
      "name": "cs storage type",
      "scope": "storage.type.cs",
      "settings": {
        "foreground": "#8b965e"
      }
    },
    {
      "name": "cs local variable",
      "scope": "entity.name.variable.local.cs",
      "settings": {
        "foreground": "#d0d370"
      }
    },
    {
      "scope": "token.info-token",
      "settings": {
        "foreground": "#579f91"
      }
    },
    {
      "scope": "token.warn-token",
      "settings": {
        "foreground": "#c75f5f"
      }
    },
    {
      "scope": "token.error-token",
      "settings": {
        "foreground": "#f44747"
      }
    },
    {
      "scope": "token.debug-token",
      "settings": {
        "foreground": "#f3b82c"
      }
    },
    {
      "name": "String interpolation",
      "scope": [
        "punctuation.definition.template-expression.begin",
        "punctuation.definition.template-expression.end",
        "punctuation.section.embedded"
      ],
      "settings": {
        "foreground": "#f3b82c"
      }
    },
    {
      "name": "Reset JavaScript string interpolation expression",
      "scope": [
        "meta.template.expression"
      ],
      "settings": {
        "foreground": "#a9c2c1e3"
      }
    },
    {
      "name": "Import module JS",
      "scope": [
        "keyword.operator.module"
      ],
      "settings": {
        "foreground": "#f3b82c"
      }
    },
    {
      "name": "js Flowtype",
      "scope": [
        "support.type.type.flowtype"
      ],
      "settings": {
        "foreground": "#579f91"
      }
    },
    {
      "name": "js Flow",
      "scope": [
        "support.type.primitive"
      ],
      "settings": {
        "foreground": "#8b965e"
      }
    },
    {
      "name": "js class prop",
      "scope": [
        "meta.property.object"
      ],
      "settings": {
        "foreground": "#d0d370"
      }
    },
    {
      "name": "js func parameter",
      "scope": [
        "variable.parameter.function.js"
      ],
      "settings": {
        "foreground": "#d0d370"
      }
    },
    {
      "name": "js template literals begin",
      "scope": [
        "keyword.other.template.begin"
      ],
      "settings": {
        "foreground": "#c75f5f"
      }
    },
    {
      "name": "js template literals end",
      "scope": [
        "keyword.other.template.end"
      ],
      "settings": {
        "foreground": "#c75f5f"
      }
    },
    {
      "name": "js template literals variable braces begin",
      "scope": [
        "keyword.other.substitution.begin"
      ],
      "settings": {
        "foreground": "#c75f5f"
      }
    },
    {
      "name": "js template literals variable braces end",
      "scope": [
        "keyword.other.substitution.end"
      ],
      "settings": {
        "foreground": "#c75f5f"
      }
    },
    {
      "name": "js operator.assignment",
      "scope": [
        "keyword.operator.assignment"
      ],
      "settings": {
        "foreground": "#f9ed41"
      }
    },
    {
      "name": "go operator",
      "scope": [
        "keyword.operator.assignment.go"
      ],
      "settings": {
        "foreground": "#8b965e"
      }
    },
    {
      "name": "go operator",
      "scope": [
        "keyword.operator.arithmetic.go",
        "keyword.operator.address.go"
      ],
      "settings": {
        "foreground": "#f3b82c"
      }
    },
    {
      "name": "Go package name",
      "scope": [
        "entity.name.package.go"
      ],
      "settings": {
        "foreground": "#8b965e"
      }
    },
    {
      "name": "elm prelude",
      "scope": [
        "support.type.prelude.elm"
      ],
      "settings": {
        "foreground": "#f9ed41"
      }
    },
    {
      "name": "elm constant",
      "scope": [
        "support.constant.elm"
      ],
      "settings": {
        "foreground": "#c75f5f"
      }
    },
    {
      "name": "template literal",
      "scope": [
        "punctuation.quasi.element"
      ],
      "settings": {
        "foreground": "#f3b82c"
      }
    },
    {
      "name": "html/pug (jade) escaped characters and entities",
      "scope": [
        "constant.character.entity"
      ],
      "settings": {
        "foreground": "#d0d370"
      }
    },
    {
      "name": "styling css pseudo-elements/classes to be able to differentiate from classes which are the same colour",
      "scope": [
        "entity.other.attribute-name.pseudo-element",
        "entity.other.attribute-name.pseudo-class"
      ],
      "settings": {
        "foreground": "#f9ed41"
      }
    },
    {
      "name": "Clojure globals",
      "scope": [
        "entity.global.clojure"
      ],
      "settings": {
        "foreground": "#8b965e"
      }
    },
    {
      "name": "Clojure symbols",
      "scope": [
        "meta.symbol.clojure"
      ],
      "settings": {
        "foreground": "#d0d370"
      }
    },
    {
      "name": "Clojure constants",
      "scope": [
        "constant.keyword.clojure"
      ],
      "settings": {
        "foreground": "#f9ed41"
      }
    },
    {
      "name": "CoffeeScript Function Argument",
      "scope": [
        "meta.arguments.coffee",
        "variable.parameter.function.coffee"
      ],
      "settings": {
        "foreground": "#d0d370"
      }
    },
    {
      "name": "Ini Default Text",
      "scope": [
        "source.ini"
      ],
      "settings": {
        "foreground": "#c75f5f"
      }
    },
    {
      "name": "Makefile prerequisities",
      "scope": [
        "meta.scope.prerequisites.makefile"
      ],
      "settings": {
        "foreground": "#d0d370"
      }
    },
    {
      "name": "Makefile text colour",
      "scope": [
        "source.makefile"
      ],
      "settings": {
        "foreground": "#8b965e"
      }
    },
    {
      "name": "Groovy import names",
      "scope": [
        "storage.modifier.import.groovy"
      ],
      "settings": {
        "foreground": "#8b965e"
      }
    },
    {
      "name": "Groovy Methods",
      "scope": [
        "meta.method.groovy"
      ],
      "settings": {
        "foreground": "#579f91"
      }
    },
    {
      "name": "Groovy Variables",
      "scope": [
        "meta.definition.variable.name.groovy"
      ],
      "settings": {
        "foreground": "#d0d370"
      }
    },
    {
      "name": "Groovy Inheritance",
      "scope": [
        "meta.definition.class.inherited.classes.groovy"
      ],
      "settings": {
        "foreground": "#c75f5f"
      }
    },
    {
      "name": "HLSL Semantic",
      "scope": [
        "support.variable.semantic.hlsl"
      ],
      "settings": {
        "foreground": "#8b965e"
      }
    },
    {
      "name": "HLSL Types",
      "scope": [
        "support.type.texture.hlsl",
        "support.type.sampler.hlsl",
        "support.type.object.hlsl",
        "support.type.object.rw.hlsl",
        "support.type.fx.hlsl",
        "support.type.object.hlsl"
      ],
      "settings": {
        "foreground": "#f3b82c"
      }
    },
    {
      "name": "SQL Variables",
      "scope": [
        "text.variable",
        "text.bracketed"
      ],
      "settings": {
        "foreground": "#d0d370"
      }
    },
    {
      "name": "types",
      "scope": [
        "support.type.swift",
        "support.type.vb.asp"
      ],
      "settings": {
        "foreground": "#8b965e"
      }
    },
    {
      "name": "heading 1, keyword",
      "scope": [
        "entity.name.function.xi"
      ],
      "settings": {
        "foreground": "#8b965e"
      }
    },
    {
      "name": "heading 2, callable",
      "scope": [
        "entity.name.class.xi"
      ],
      "settings": {
        "foreground": "#f9ed41"
      }
    },
    {
      "name": "heading 3, property",
      "scope": [
        "constant.character.character-class.regexp.xi"
      ],
      "settings": {
        "foreground": "#d0d370"
      }
    },
    {
      "name": "heading 4, type, class, interface",
      "scope": [
        "constant.regexp.xi"
      ],
      "settings": {
        "foreground": "#f3b82c"
      }
    },
    {
      "name": "heading 5, enums, preprocessor, constant, decorator",
      "scope": [
        "keyword.control.xi"
      ],
      "settings": {
        "foreground": "#f9ed41"
      }
    },
    {
      "name": "heading 6, number",
      "scope": [
        "invalid.xi"
      ],
      "settings": {
        "foreground": "#a9c2c1e3"
      }
    },
    {
      "name": "string",
      "scope": [
        "beginning.punctuation.definition.quote.markdown.xi"
      ],
      "settings": {
        "foreground": "#c75f5f"
      }
    },
    {
      "name": "comments",
      "scope": [
        "beginning.punctuation.definition.list.markdown.xi"
      ],
      "settings": {
        "foreground": "#686451"
      }
    },
    {
      "name": "link",
      "scope": [
        "constant.character.xi"
      ],
      "settings": {
        "foreground": "#579f91"
      }
    },
    {
      "name": "accent",
      "scope": [
        "accent.xi"
      ],
      "settings": {
        "foreground": "#579f91"
      }
    },
    {
      "name": "wikiword",
      "scope": [
        "wikiword.xi"
      ],
      "settings": {
        "foreground": "#c75f5f"
      }
    },
    {
      "name": "language operators like '+', '-' etc",
      "scope": [
        "constant.other.color.rgb-value.xi"
      ],
      "settings": {
        "foreground": "#ffffff"
      }
    },
    {
      "name": "elements to dim",
      "scope": [
        "punctuation.definition.tag.xi"
      ],
      "settings": {
        "foreground": "#686451"
      }
    },
    {
      "name": "C++/C#",
      "scope": [
        "entity.name.label.cs",
        "entity.name.scope-resolution.function.call",
        "entity.name.scope-resolution.function.definition"
      ],
      "settings": {
        "foreground": "#8b965e"
      }
    },
    {
      "name": "Markdown underscore-style headers",
      "scope": [
        "entity.name.label.cs",
        "markup.heading.setext.1.markdown",
        "markup.heading.setext.2.markdown"
      ],
      "settings": {
        "foreground": "#d0d370"
      }
    },
    {
      "name": "meta.brace.square",
      "scope": [
        " meta.brace.square"
      ],
      "settings": {
        "foreground": "#a9c2c1e3"
      }
    },
    {
      "name": "Comments",
      "scope": "comment, punctuation.definition.comment",
      "settings": {
        "fontStyle": "italic",
        "foreground": "#686451"
      }
    },
    {
      "name": "[VSCODE-CUSTOM] Markdown Quote",
      "scope": "markup.quote.markdown",
      "settings": {
        "foreground": "#686451"
      }
    },
    {
      "name": "punctuation.definition.block.sequence.item.yaml",
      "scope": "punctuation.definition.block.sequence.item.yaml",
      "settings": {
        "foreground": "#a9c2c1e3"
      }
    },
    {
      "scope": [
        "constant.language.symbol.elixir"
      ],
      "settings": {
        "foreground": "#f9ed41"
      }
    },
    {
      "name": "js/ts italic",
      "scope": "entity.other.attribute-name.js,entity.other.attribute-name.ts,entity.other.attribute-name.jsx,entity.other.attribute-name.tsx,variable.parameter,variable.language.super",
      "settings": {
        "fontStyle": "italic"
      }
    },
    {
      "name": "comment",
      "scope": "comment.line.double-slash,comment.block.documentation",
      "settings": {
        "fontStyle": "italic"
      }
    },
    {
      "name": "Python Keyword Control",
      "scope": "keyword.control.import.python,keyword.control.flow.python",
      "settings": {
        "fontStyle": "italic"
      }
    },
    {
      "name": "markup.italic.markdown",
      "scope": "markup.italic.markdown",
      "settings": {
        "fontStyle": "italic"
      }
    }
  ],
  "colors": {
    "foreground": "#c3c9be",
    "focusBorder": "#a59854f5",
    "selection.background": "#908457",
    "scrollbar.shadow": "#1d1a1056",
    "activityBar.foreground": "#dfe6e6e3",
    "activityBar.background": "#3d3729",
    "activityBar.inactiveForeground": "#8e887f",
    "activityBarBadge.foreground": "#cdcdcd",
    "activityBarBadge.background": "#2a2720",
    "activityBar.border": "#3d372942",
    "activityBar.activeBackground": "#433d2e",
    "sideBar.background": "#433d2e",
    "sideBar.foreground": "#ffffff91",
    "sideBarSectionHeader.background": "#453e30",
    "sideBarSectionHeader.foreground": "#dfe6e6e3",
    "sideBarSectionHeader.border": "#3d3829",
    "sideBarTitle.foreground": "#dfe6e6e3",
    "sideBar.border": "#3d3829",
    "list.inactiveSelectionBackground": "#564c39",
    "list.inactiveSelectionForeground": "#fcfcfc",
    "list.hoverBackground": "#5c5126f1",
    "list.hoverForeground": "#fcfcfc",
    "list.activeSelectionBackground": "#e8a70b5e",
    "list.activeSelectionForeground": "#dfe6e6e3",
    "tree.indentGuidesStroke": "#564f39",
    "list.dropBackground": "#564d39",
    "list.highlightForeground": "#f24545",
    "list.focusBackground": "#5a4401a9",
    "list.focusForeground": "#fcfcfc",
    "listFilterWidget.background": "#362f24",
    "listFilterWidget.outline": "#00000000",
    "listFilterWidget.noMatchesOutline": "#f94144",
    "statusBar.foreground": "#dbd1b970",
    "statusBar.background": "#3d3729",
    "statusBarItem.hoverBackground": "#7d6814cd",
    "statusBar.border": "#ffffff00",
    "statusBar.debuggingBackground": "#f94144",
    "statusBar.debuggingForeground": "#fcfcfc",
    "statusBar.debuggingBorder": "#ffffff00",
    "statusBar.noFolderBackground": "#322d22",
    "statusBar.noFolderForeground": "#ffffff36",
    "statusBar.noFolderBorder": "#ffffff00",
    "statusBarItem.remoteBackground": "#f94144",
    "statusBarItem.remoteForeground": "#fcfcfc",
    "titleBar.activeBackground": "#3d3729",
    "titleBar.activeForeground": "#fcfcfcad",
    "titleBar.inactiveBackground": "#322d22",
    "titleBar.inactiveForeground": "#8e8a7f70",
    "titleBar.border": "#ffffff00",
    "menubar.selectionForeground": "#ffffff",
    "menubar.selectionBackground": "#8a6816cd",
    "menubar.selectionBorder": "#3d3729",
    "menu.foreground": "#fcfcfccd",
    "menu.background": "#3d3829",
    "menu.selectionForeground": "#ffffff",
    "menu.selectionBackground": "#73591ac5",
    "menu.selectionBorder": "#ffffff00",
    "menu.separatorBackground": "#564d39",
    "menu.border": "#302a20c5",
    "button.background": "#908457",
    "button.foreground": "#fcfcfc",
    "button.hoverBackground": "#6c6341",
    "button.secondaryForeground": "#fcfcfc",
    "button.secondaryBackground": "#565039",
    "button.secondaryHoverBackground": "#403b2b",
    "input.background": "#3d3729",
    "input.border": "#3d3729",
    "input.foreground": "#fcfcfc",
    "inputOption.activeBackground": "#2e281c",
    "inputOption.activeBorder": "#241e1091",
    "inputOption.activeForeground": "#f7f7f7d1",
    "input.placeholderForeground": "#8e8a7f",
    "textLink.foreground": "#ea4151",
    "editor.background": "#3d3729",
    "editor.foreground": "#a9c2c1e3",
    "editorLineNumber.foreground": "#5a5647",
    "editorCursor.foreground": "#fcfcfc",
    "editorCursor.background": "#000000",
    "editor.selectionBackground": "#1d1907d9",
    "editor.inactiveSelectionBackground": "#4f472ecf",
    "editorWhitespace.foreground": "#f0e8da32",
    "editor.selectionHighlightBackground": "#add6ff00",
    "editor.selectionHighlightBorder": "#3ba789",
    "editor.findMatchBackground": "#320707a7",
    "editor.findMatchBorder": "#e0cc2f",
    "editor.findMatchHighlightBackground": "#32010168",
    "editor.findMatchHighlightBorder": "#ffffff00",
    "editor.findRangeHighlightBackground": "#49433066",
    "editor.findRangeHighlightBorder": "#ffffff00",
    "editor.rangeHighlightBackground": "#ffffff0b",
    "editor.rangeHighlightBorder": "#ffffff00",
    "editor.hoverHighlightBackground": "#eb01f240",
    "editor.wordHighlightStrongBackground": "#17528897",
    "editor.wordHighlightBackground": "#575757b8",
    "editor.lineHighlightBackground": "#ffffff0A",
    "editor.lineHighlightBorder": "#ffffff00",
    "editorLineNumber.activeForeground": "#e8e8e8",
    "editorLink.activeForeground": "#17c2ea",
    "editorIndentGuide.background": "#4b4732",
    "editorIndentGuide.activeBackground": "#579f91",
    "editorRuler.foreground": "#4f493a",
    "editorBracketMatch.background": "#000000a9",
    "editorBracketMatch.border": "#e62375b7",
    "editor.foldBackground": "#1710034d",
    "editorOverviewRuler.background": "#25252500",
    "editorOverviewRuler.border": "#7f7f7f4d",
    "editorError.foreground": "#f94144",
    "editorError.background": "#b73a341c",
    "editorError.border": "#ffffff00",
    "editorWarning.foreground": "#f8ea1e",
    "editorWarning.background": "#a9904016",
    "editorWarning.border": "#ffffff00",
    "editorInfo.foreground": "#2dd5e6",
    "editorInfo.background": "#44aebf16",
    "editorInfo.border": "#4490BF00",
    "editorGutter.background": "#3d3729",
    "editorGutter.modifiedBackground": "#5d95c2",
    "editorGutter.addedBackground": "#90be6d",
    "editorGutter.deletedBackground": "#d94648",
    "editorGutter.foldingControlForeground": "#908257",
    "editorCodeLens.foreground": "#907c57",
    "editorGroup.border": "#3b33208f",
    "diffEditor.insertedTextBackground": "#a1800014",
    "diffEditor.insertedTextBorder": "#ffffff00",
    "diffEditor.removedTextBackground": "#00000036",
    "diffEditor.removedTextBorder": "#ffffff00",
    "diffEditor.border": "#ffffff00",
    "panel.background": "#322d22",
    "panel.border": "#ffffff00",
    "panelTitle.activeBorder": "#fcfcfc",
    "panelTitle.activeForeground": "#fcfcfc",
    "panelTitle.inactiveForeground": "#8e8a7f",
    "badge.background": "#150f00b3",
    "badge.foreground": "#cbcbcbd3",
    "terminal.foreground": "#fcfcfcc1",
    "terminal.selectionBackground": "#f9c74f33",
    "terminalCursor.background": "#000000",
    "terminalCursor.foreground": "#ffffff",
    "terminal.border": "#433d30e7",
    "terminal.ansiBlack": "#000000",
    "terminal.ansiBlue": "#1a5094",
    "terminal.ansiBrightBlack": "#1b1b1b",
    "terminal.ansiBrightBlue": "#137fdb",
    "terminal.ansiBrightCyan": "#2bcbad",
    "terminal.ansiBrightGreen": "#6ec72a",
    "terminal.ansiBrightMagenta": "#ce25de",
    "terminal.ansiBrightRed": "#ea3336",
    "terminal.ansiBrightWhite": "#e2e2e2",
    "terminal.ansiBrightYellow": "#eac914",
    "terminal.ansiCyan": "#43aa97",
    "terminal.ansiGreen": "#57902b",
    "terminal.ansiMagenta": "#a516b2",
    "terminal.ansiRed": "#bc2a2c",
    "terminal.ansiWhite": "#cfcfcf",
    "terminal.ansiYellow": "#bc9f00",
    "breadcrumb.background": "#3d3729",
    "breadcrumb.foreground": "#fcfcfc5a",
    "breadcrumb.focusForeground": "#fcfcfc",
    "editorGroupHeader.border": "#ffffff00",
    "editorGroupHeader.tabsBackground": "#433d2e",
    "editorGroupHeader.tabsBorder": "#3d3629e1",
    "tab.activeForeground": "#fcfcfc",
    "tab.border": "#363024d1",
    "tab.activeBackground": "#3d3729",
    "tab.activeBorder": "#f9f9f900",
    "tab.activeBorderTop": "#f94144",
    "tab.inactiveBackground": "#433d2e",
    "tab.inactiveForeground": "#8a8a8ad5",
    "tab.hoverBackground": "#907a22a9",
    "tab.hoverForeground": "#fcfcfc",
    "tab.hoverBorder": "#ffffff00",
    "scrollbarSlider.background": "#624b1f3a",
    "scrollbarSlider.hoverBackground": "#624b1f8d",
    "scrollbarSlider.activeBackground": "#624b1fdb",
    "progressBar.background": "#b2af19",
    "widget.shadow": "#2e2a1f",
    "editorWidget.foreground": "#fcfcfc",
    "editorWidget.background": "#3d3729",
    "editorWidget.resizeBorder": "#907f57",
    "pickerGroup.border": "#ffffff00",
    "pickerGroup.foreground": "#f09c2f",
    "debugToolBar.background": "#342e22",
    "debugToolBar.border": "#2e281f81",
    "notifications.foreground": "#fbfbfbaf",
    "notifications.background": "#322c1b",
    "notificationToast.border": "#564f39",
    "notificationsErrorIcon.foreground": "#f94144",
    "notificationsWarningIcon.foreground": "#f8961e",
    "notificationsInfoIcon.foreground": "#67b6c9",
    "notificationCenter.border": "#2a2518",
    "notificationCenterHeader.foreground": "#fcfcfc",
    "notificationCenterHeader.background": "#2a2518",
    "notifications.border": "#2a2518",
    "gitDecoration.addedResourceForeground": "#b7d16e",
    "gitDecoration.conflictingResourceForeground": "#e47c53",
    "gitDecoration.deletedResourceForeground": "#db484b",
    "gitDecoration.ignoredResourceForeground": "#716040",
    "gitDecoration.modifiedResourceForeground": "#f2b933",
    "gitDecoration.stageDeletedResourceForeground": "#b04d4e",
    "gitDecoration.stageModifiedResourceForeground": "#f8961e",
    "gitDecoration.submoduleResourceForeground": "#738290",
    "gitDecoration.untrackedResourceForeground": "#719f91",
    "editorMarkerNavigation.background": "#322c1b",
    "editorMarkerNavigationError.background": "#ec484b",
    "editorMarkerNavigationWarning.background": "#fdb834",
    "editorMarkerNavigationInfo.background": "#6cb8c4",
    "merge.currentHeaderBackground": "#5e422e",
    "merge.currentContentBackground": "#30271a",
    "merge.incomingHeaderBackground": "#307745",
    "merge.incomingContentBackground": "#273f25",
    "merge.commonHeaderBackground": "#383838",
    "merge.commonContentBackground": "#282828",
    "editorSuggestWidget.background": "#2e291d",
    "editorSuggestWidget.border": "#302d2500",
    "editorSuggestWidget.foreground": "#d9d9d9c1",
    "editorSuggestWidget.highlightForeground": "#e24b4b",
    "editorSuggestWidget.selectedBackground": "#473814c5",
    "editorHoverWidget.foreground": "#fcfcfcb3",
    "editorHoverWidget.background": "#322c20",
    "editorHoverWidget.border": "#564f39c5",
    "peekView.border": "#2e291cc3",
    "peekViewEditor.background": "#322c20",
    "peekViewEditorGutter.background": "#322c20",
    "peekViewEditor.matchHighlightBackground": "#fba27200",
    "peekViewEditor.matchHighlightBorder": "#f0a03e",
    "peekViewResult.background": "#322c20",
    "peekViewResult.fileForeground": "#fcfcfcb7",
    "peekViewResult.lineForeground": "#fcfcfcb9",
    "peekViewResult.matchHighlightBackground": "#f8961e4d",
    "peekViewResult.selectionBackground": "#90845733",
    "peekViewResult.selectionForeground": "#fcfcfcbd",
    "peekViewTitle.background": "#322c20",
    "peekViewTitleDescription.foreground": "#fcfcfcb3",
    "peekViewTitleLabel.foreground": "#fcfcfcb7",
    "icon.foreground": "#c3c9be",
    "checkbox.background": "#3d3729",
    "checkbox.foreground": "#fcfcfc",
    "checkbox.border": "#3d3729",
    "dropdown.background": "#3d3729",
    "dropdown.foreground": "#fcfcfc",
    "dropdown.border": "#3d3729",
    "minimapGutter.addedBackground": "#90be6d",
    "minimapGutter.modifiedBackground": "#5d95c2",
    "minimapGutter.deletedBackground": "#d94648",
    "minimap.findMatchHighlight": "#320707a7",
    "minimap.selectionHighlight": "#1d1907d9",
    "minimap.errorHighlight": "#f94144",
    "minimap.warningHighlight": "#f8ea1e",
    "minimap.background": "#3d3729",
    "sideBar.dropBackground": "#564d39",
    "editorGroup.emptyBackground": "#3d3729",
    "panelSection.border": "#433d30e7",
    "statusBarItem.activeBackground": "#FFFFFF25",
    "settings.headerForeground": "#c3c9be",
    "settings.focusedRowBackground": "#ffffff07",
    "walkThrough.embeddedEditorBackground": "#00000050",
    "breadcrumb.activeSelectionForeground": "#fcfcfc",
    "editorGutter.commentRangeForeground": "#908257",
    "debugExceptionWidget.background": "#342e22",
    "debugExceptionWidget.border": "#2e281f81"
  }
}